{
  "hit_points": 16,
  "condition_immunities": "",
  "languages": "",
  "senses": "passive Perception 11",
  "challenge_rating": "1/2",
  "damage_immunities": "",
  "type": "beast",
  "speed": "0 ft., swim 40 ft.",
  "damage_vulnerabilities": "",
  "damage_resistances": "",
  "skills": {},
  "armor_class": 13,
  "Uuid": 137,
  "size": "Large",
  "subtype": "",
  "saving_throws": {},
  "hit_dice": "3d10",
  "name": "Giant Sea Horse",
  "special_abilities": [
    {
      "attack_bonus": 0,
      "damage_dice": "2d6",
      "name": "Charge",
      "desc": "If the sea horse moves at least 20 ft. straight toward a target and then hits it with a ram attack on the same turn, the target takes an extra 7 (2d6) bludgeoning damage. If the target is a creature, it must succeed on a DC 11 Strength saving throw or be knocked prone."
    },
    {
      "attack_bonus": 0,
      "name": "Water Breathing",
      "desc": "The sea horse can breathe only underwater."
    }
  ],
  "attributes": {
    "dexterity": 15,
    "constitution": 11,
    "strength": 12,
    "charisma": 5,
    "intelligence": 2,
    "wisdom": 12
  },
  "alignment": "unaligned",
  "actions": [{
    "attack_bonus": 3,
    "damage_dice": "1d6",
    "name": "Ram",
    "damage_bonus": 1,
    "desc": "Melee Weapon Attack: +3 to hit, reach 5 ft., one target. Hit: 4 (1d6 + 1) bludgeoning damage."
  }]
}